README.rst
setup.py
django_fcm_vp.egg-info/PKG-INFO
django_fcm_vp.egg-info/SOURCES.txt
django_fcm_vp.egg-info/dependency_links.txt
django_fcm_vp.egg-info/not-zip-safe
django_fcm_vp.egg-info/requires.txt
django_fcm_vp.egg-info/top_level.txt
fcm/__init__.py
fcm/admin.py
fcm/apps.py
fcm/forms.py
fcm/models.py
fcm/serializers.py
fcm/tests.py
fcm/urls.py
fcm/utils.py
fcm/views.py
fcm/management/__init__.py
fcm/management/commands/__init__.py
fcm/management/commands/fcm_messenger.py
fcm/management/commands/fcm_urls.py
fcm/migrations/0001_initial.py
fcm/migrations/__init__.py